purely/__init__.py
purely/core.py
purely/curry.py
purely/di.py
purely/dispatch.py
purely/result.py
purely-1.2.dist-info/METADATA
purely-1.2.dist-info/WHEEL
purely-1.2.dist-info/RECORD
