Metadata-Version: 2.4
Name: purely
Version: 1.2
Summary: Unobstrusive functional programming in Python.
Author-email: Alejandro Piad <apiad@apiad.net>
Classifier: License :: OSI Approved :: MIT License
Classifier: Operating System :: OS Independent
Classifier: Programming Language :: Python :: 3.12
Requires-Python: >=3.12
